fastphrase-0.0.14.dist-info/METADATA
fastphrase-0.0.14.dist-info/WHEEL
fastphrase-0.0.14.dist-info/entry_points.txt
fastphrase/__about__.py
fastphrase/__init__.py
fastphrase/__main__.py
fastphrase/cli/__init__.py
fastphrase/cli/app.py
fastphrase/core/__init__.py
fastphrase/core/passphraser.py
fastphrase/core/pathkeeper.py
fastphrase/core/wordlist.py
fastphrase/data/dict/bip0039.txt
fastphrase/data/dict/eff_long.txt
fastphrase/data/dict/eff_short1.txt
fastphrase/data/dict/eff_short2.txt
fastphrase-0.0.14.dist-info/RECORD
